CommonMethods/EpochConverter.py
CommonMethods/ExcelOperations.py
CommonMethods/Miscellaneous.py
CommonMethods/__init__.py
CommonPythonMethods-0.0.1.dist-info/METADATA
CommonPythonMethods-0.0.1.dist-info/WHEEL
CommonPythonMethods-0.0.1.dist-info/top_level.txt
CommonPythonMethods-0.0.1.dist-info/RECORD
